gitget.py
git_get-0.2.0.dist-info/entry_points.txt
git_get-0.2.0.dist-info/WHEEL
git_get-0.2.0.dist-info/METADATA
git_get-0.2.0.dist-info/RECORD
