Metadata-Version: 2.4
Name: git-get
Version: 0.2.0
Summary: Automatically clone Git repos.
Author-email: Daniel Rocha <daniel@rocha.io>
Requires-Python: >=3.10
Requires-Dist: rich>=12.6.0
Requires-Dist: typer>=0.6.1
Project-URL: homepage, https://github.com/danroc/git-get
